ass/__init__.py
ass/_util.py
ass/data.py
ass/document.py
ass/line.py
ass/renderer.py
ass/section.py
ass-1.0.3.dist-info/licenses/LICENSE
ass-1.0.3.dist-info/WHEEL
ass-1.0.3.dist-info/METADATA
ass-1.0.3.dist-info/RECORD
