Metadata-Version: 2.4
Name: ass
Version: 1.0.3
Summary: A library for parsing and manipulating Advanced SubStation Alpha subtitle files.
Author: Tony Young, FichteFoll, Myaamori
Author-email: Tony Young <author@example.com>, FichteFoll <fichtefoll2@googlemail.com>
License-Expression: MIT
License-File: LICENSE
Classifier: Development Status :: 5 - Production/Stable
Classifier: Intended Audience :: Developers
Classifier: Operating System :: OS Independent
Classifier: Programming Language :: Python :: 3
Classifier: Topic :: Multimedia :: Video
Classifier: Topic :: Software Development :: Libraries
Classifier: Topic :: Text Processing :: Markup
Maintainer: FichteFoll
Maintainer-email: FichteFoll <fichtefoll2@googlemail.com>
Requires-Python: >=3.8.1
Project-URL: Homepage, http://github.com/chireiden/python-ass
Project-URL: Issues, http://github.com/chireiden/python-ass/issues
Project-URL: Release Notes, https://github.com/chireiden/python-ass/releases
